{
    "background": [0.1, 0.1, 0.1],
    "camera": {
        "position": [0.0, 12.5, 0.0],
        "target": [0.0, 0.0, 0.0],
        "up": [-1.0, 0.0, 0.0]
    },
    "models": [
        {
            "type": "plane",
            "shader": "texture",
            "material": {
                "color": [0.85, 1.0, 0.0],
                "specular": [0.0, 1.0, 0.0],
                "shininess": 4
            },
            "texture": {
                "url": "images/dog.jpg",
                "scale": [3, 3]
            },
            "center": [1.0, 1.0, -1.0],
            "size": [4.0, 1.0, 4.0]
        },
        {
            "type": "sphere",
            "shader": "color",
            "material": {
                "color": [0.66, 0.66, 0.66],
                "specular": [1.0, 1.0, 1.0],
                "shininess": 10
            },
            "center": [0.0, 1.0, -3.0],
            "size": [2.0, 2.0, 2.0]
        },
        {
            "type": "custom",
            "shader": "color",
            "material": {
                "color": [1.0, 0.876, 0.138],
                "specular": [1.0, 1.0, 1.0],
                "shininess": 30
            },
            "center": [1.5, 0, 0.0],
            "size": [8.0, 2.0, 6.0]
        }
    ],
    "light": {
        "ambient": [0.20, 0.15, 0.45],
        "point_lights": [
            {
                "position": [0.5, 1.0, 3.5],
                "color": [0.5, 0.5, 0.5]
            },
            {
                "position": [-3.0, -0.5, 0],
                "color": [0.0, 0.374, 0.0]
            }
        ]
    }
}
